valve_gfx_ci/executor/server/__init__.py
valve_gfx_ci/executor/server/app.py
valve_gfx_ci/executor/server/boots.py
valve_gfx_ci/executor/server/boots_db.py
valve_gfx_ci/executor/server/config.py
valve_gfx_ci/executor/server/dhcpd.py
valve_gfx_ci/executor/server/dut.py
valve_gfx_ci/executor/server/executor.py
valve_gfx_ci/executor/server/gitlab.py
valve_gfx_ci/executor/server/job.py
valve_gfx_ci/executor/server/logger.py
valve_gfx_ci/executor/server/mars.py
valve_gfx_ci/executor/server/message.py
valve_gfx_ci/executor/server/minioclient.py
valve_gfx_ci/executor/server/socketactivation.py
valve_gfx_ci/executor/server/tftpd.py
valve_gfx_ci/executor/server/android/__init__.py
valve_gfx_ci/executor/server/android/fastbootd.py
valve_gfx_ci/executor/server/android/mkbootimg.py
valve_gfx_ci/executor/server/job_templates/bootloop.yml.j2
valve_gfx_ci/executor/server/job_templates/cache_reset.yml.j2
valve_gfx_ci/executor/server/job_templates/interactive.yml.j2
valve_gfx_ci/executor/server/job_templates/register.yml.j2
valve_gfx_ci/executor/server/pdu/__init__.py
valve_gfx_ci/executor/server/pdu/daemon.py
valve_gfx_ci/executor/server/pdu/drivers/__init__.py
valve_gfx_ci/executor/server/pdu/drivers/apc.py
valve_gfx_ci/executor/server/pdu/drivers/cyberpower.py
valve_gfx_ci/executor/server/pdu/drivers/devantech.py
valve_gfx_ci/executor/server/pdu/drivers/dummy.py
valve_gfx_ci/executor/server/pdu/drivers/kernelchip.py
valve_gfx_ci/executor/server/pdu/drivers/shelly.py
valve_gfx_ci/executor/server/pdu/drivers/snmp.py
valve_gfx_ci/executor/server/pdu/drivers/tasmota.py
valve_gfx_ci/executor/server/pdu/drivers/usbhub.py
valve_gfx_ci/executor/server/pdu/drivers/virtual.py
valve_gfx_ci/executor/server/templates/boots_db.yml.j2
valve_gfx_ci/executor/server/templates/gitlab_runner_config.toml.j2
valve_gfx_ci/executor/server/tests/__init__.py
valve_gfx_ci/executor/server/tests/sample_job.yml
valve_gfx_ci/executor/server/tests/test_boots.py
valve_gfx_ci.executor.server-0.0.3.dist-info/LICENSE
valve_gfx_ci.executor.server-0.0.3.dist-info/METADATA
valve_gfx_ci.executor.server-0.0.3.dist-info/WHEEL
valve_gfx_ci.executor.server-0.0.3.dist-info/entry_points.txt
valve_gfx_ci.executor.server-0.0.3.dist-info/top_level.txt
valve_gfx_ci.executor.server-0.0.3.dist-info/RECORD
