Metadata-Version: 2.1
Name: valve_gfx_ci.executor.server
Version: 0.0.3
Summary: Valve GFX CI's executor
Home-page: https://gitlab.freedesktop.org/gfx-ci/ci-tron/-/tree/master/executor/server
Author: Martin Roukala
Author-email: martin.roukala@mupuf.org
Project-URL: Bug Tracker, https://gitlab.freedesktop.org/gfx-ci/ci-tron/issues
Classifier: Programming Language :: Python :: 3
Classifier: License :: OSI Approved :: MIT License
Classifier: Operating System :: OS Independent
Requires-Python: >=3.6
License-File: LICENSE
Requires-Dist: requests <3,>=2
Requires-Dist: easysnmp ==0.2.5
Requires-Dist: Flask <3,>=2.2
Requires-Dist: pydantic <3,>=2
Requires-Dist: python-dateutil <3,>=2.8
Requires-Dist: PyYAML <7,>=6
Requires-Dist: minio <7.1,>=7.0
Requires-Dist: inotify-simple ==1.3.5
Requires-Dist: Jinja2 ==3.0.3
Requires-Dist: deepdiff ==5.7.0
Requires-Dist: psutil <6,>=5.9
Requires-Dist: waitress <3,>=2.1.2
Requires-Dist: requests-unixsocket2 <1,>=0.4
Requires-Dist: CacheControl[filecache] <1,>=0.14
Requires-Dist: urllib3 <2
Requires-Dist: pyusb <2,>=1.2
Requires-Dist: backports.cached-property ; python_version < "3.8"
